core/__init__.py
core/utils.py
karate-0.0.1.dist-info/LICENSE
karate-0.0.1.dist-info/METADATA
karate-0.0.1.dist-info/WHEEL
karate-0.0.1.dist-info/top_level.txt
karate-0.0.1.dist-info/RECORD
