Metadata-Version: 2.1
Name: karate
Version: 0.0.1
Summary: Python library for topological data analysis of time series
Home-page: https://github.com/doerlbh/karate
Author: Baihan Lin
Author-email: doerlbh@gmail.com
License: GPLv3
Project-URL: Bug Tracker, https://github.com/doerlbh/karate/issues
Classifier: Programming Language :: Python :: 3
Classifier: License :: OSI Approved :: GNU General Public License v3 (GPLv3)
Classifier: Operating System :: OS Independent
Requires-Python: >=3.6
License-File: LICENSE
Requires-Dist: numpy (>=1.16.5)
Requires-Dist: pandas
